{
  "req": {
    "appCode": "YDUTE5gscDZ229CW",
    "gameVersion": "1.0",
    "version": "1.0.14",
    "randStr": "Qk2mXHuAH1JWKF37",
    "platform": "PlayStation"
  },
  "rsp": {
    "resources": [
      {
        "name": "main",
        "version": "5605008-115",
        "path": "https://beyond.hg-cdn.com/YDUTE5gscDZ229CW/1.0/resource/PlayStation/main/5605008-115_ehITTPqpgMoZ1KxM/files"
      },
      {
        "name": "initial",
        "version": "5605008-115",
        "path": "https://beyond.hg-cdn.com/YDUTE5gscDZ229CW/1.0/resource/PlayStation/initial/5605008-115_kPXCdQJDO0w8nCbW/files"
      }
    ],
    "configs": "{\"kick_flag\":true}",
    "res_version": "initial_5605008-115_main_5605008-115",
    "patch_index_path": "",
    "domain": "https://beyond.hg-cdn.com"
  }
}
