{
  "isInitial": true,
  "files": [
    {
      "index": 1,
      "name": "VFS/1CDDBF1F/1CDDBF1F.blc",
      "hash": "e89e66548785cac79603aa1efa0a82a6",
      "size": 228,
      "type": 4,
      "md5": "e89e66548785cac79603aa1efa0a82a6",
      "urlPath": null,
      "manifest": 7
    },
    {
      "index": 2,
      "name": "VFS/1CDDBF1F/2106E479C7C2CB271BEB61BDCA5A2390.chk",
      "hash": null,
      "size": 47742270,
      "type": 4,
      "md5": "a76d0ee9f7410a38c9420bbf4e1b3f41",
      "urlPath": null,
      "manifest": 0
    },
    {
      "index": 3,
      "name": "VFS/DAFE52C9/DAFE52C9.blc",
      "hash": "53b0b40a7331f948251dd5000f07dc12",
      "size": 411,
      "type": 5,
      "md5": "53b0b40a7331f948251dd5000f07dc12",
      "urlPath": null,
      "manifest": 7
    },
    {
      "index": 4,
      "name": "VFS/DAFE52C9/42665C50B237EEF2A5803D16D1FF68B1.chk",
      "hash": null,
      "size": 42404,
      "type": 5,
      "md5": "e2cf728b95ff6e6c2df045356f2535ff",
      "urlPath": null,
      "manifest": 0
    },
    {
      "index": 5,
      "name": "VFS/DAFE52C9/81EAEA6EE5343CAED6154B7DA16C165D.chk",
      "hash": null,
      "size": 1747,
      "type": 5,
      "md5": "a118043bf9c68e42c52f65ca672e2663",
      "urlPath": null,
      "manifest": 0
    },
    {
      "index": 6,
      "name": "VFS/07A1BB91/07A1BB91.blc",
      "hash": "26be10d39100cd6328e58a56c5eba3bc",
      "size": 379,
      "type": 1,
      "md5": "26be10d39100cd6328e58a56c5eba3bc",
      "urlPath": null,
      "manifest": 7
    },
    {
      "index": 7,
      "name": "VFS/07A1BB91/88C7FF41D3BFFF67F3F43240D211A849.chk",
      "hash": null,
      "size": 85554,
      "type": 1,
      "md5": "b1de04d82878df42e90842d228de2334",
      "urlPath": null,
      "manifest": 0
    },
    {
      "index": 8,
      "name": "VFS/07A1BB91/E206D4FC1A2E174762FE3A0B5D449567.chk",
      "hash": null,
      "size": 7704472,
      "type": 1,
      "md5": "6f47feafa422a0993ab5680c7832894d",
      "urlPath": null,
      "manifest": 0
    },
    {
      "index": 9,
      "name": "VFS/0CE8FA57/0CE8FA57.blc",
      "hash": "77207161a45180c177acc6d56cae3841",
      "size": 114728,
      "type": 2,
      "md5": "77207161a45180c177acc6d56cae3841",
      "urlPath": null,
      "manifest": 3
    },
    {
      "index": 10,
      "name": "VFS/0CE8FA57/734B5A1B55B973C9475E706E4FE759DD.chk",
      "hash": null,
      "size": 153592043,
      "type": 2,
      "md5": "6256e2b8bc9c14976d52e793ed0ead78",
      "urlPath": null,
      "manifest": 4
    },
    {
      "index": 11,
      "name": "VFS/3C9D9D2D/3C9D9D2D.blc",
      "hash": "665da99345b26f21ddb9a28db023ce51",
      "size": 237,
      "type": 3,
      "md5": "665da99345b26f21ddb9a28db023ce51",
      "urlPath": null,
      "manifest": 7
    },
    {
      "index": 12,
      "name": "VFS/3C9D9D2D/DF901B244B5F378CF9EA73101AC9C83E.chk",
      "hash": null,
      "size": 292136,
      "type": 3,
      "md5": "8c449fda5d6e9c43d0f4525a78a0dbae",
      "urlPath": null,
      "manifest": 0
    }
  ],
  "types": null,
  "version": null,
  "rebootVersion": ""
}
