{
  "req": {
    "appCode": "6LL0KJuqHBVz33WK",
    "gameVersion": "1.1",
    "version": "1.1.9",
    "randStr": "RfPNtRXLwX2my3ep",
    "platform": "Windows"
  },
  "rsp": {
    "resources": [
      {
        "name": "main",
        "version": "5928852-10",
        "path": "https://beyond.hycdn.cn/6LL0KJuqHBVz33WK/1.1/resource/Windows/main/5928852-10_2pOR4EkXaGODnS5V/files"
      },
      {
        "name": "initial",
        "version": "5928852-10",
        "path": "https://beyond.hycdn.cn/6LL0KJuqHBVz33WK/1.1/resource/Windows/initial/5928852-10_JoK0vb5SnST3L5S7/files"
      }
    ],
    "configs": "{\"kick_flag\":false}",
    "res_version": "initial_5928852-10_main_5928852-10",
    "patch_index_path": "",
    "domain": "https://beyond.hycdn.cn"
  }
}
